cheatsheetify/__init__.py
cheatsheetify/__main__.py
cheatsheetify/cheatsheet_generator.py
cheatsheetify/core.py
cheatsheetify/fonts/FiraCode.ttf
cheatsheetify/fonts/Inter-Italic.ttf
cheatsheetify/fonts/Inter-Italic.ttf:Zone.Identifier
cheatsheetify/fonts/Inter.ttf
cheatsheetify/pdf_generator.py
cheatsheetify/themes.py
cheatsheetify-0.1.2.dist-info/LICENSE
cheatsheetify-0.1.2.dist-info/METADATA
cheatsheetify-0.1.2.dist-info/WHEEL
cheatsheetify-0.1.2.dist-info/RECORD
