Metadata-Version: 2.1
Name: cheatsheetify
Version: 0.1.2
Summary: cheatsheetify is a command-line tool that generates PDF versions of cheatsheets for popular command-line tools
License: MIT
Author: HYP3R00T
Author-email: hyperoot.tech@proton.me
Requires-Python: >=3.10,<4.0
Classifier: License :: OSI Approved :: MIT License
Classifier: Programming Language :: Python :: 3
Classifier: Programming Language :: Python :: 3.10
Classifier: Programming Language :: Python :: 3.11
Classifier: Programming Language :: Python :: 3.12
Requires-Dist: fpdf2 (>=2.7.8,<3.0.0)
Requires-Dist: mkdocs-material (>=9.5.20,<10.0.0)
Requires-Dist: termynal (>=0.12.1,<0.13.0)
Requires-Dist: tldr (>=3.2.0,<4.0.0)
Requires-Dist: typer (>=0.12.3,<0.13.0)
